logneuron/__init__.py
logneuron/cli.py
logneuron-0.1.0.dist-info/METADATA
logneuron-0.1.0.dist-info/WHEEL
logneuron-0.1.0.dist-info/entry_points.txt
logneuron-0.1.0.dist-info/top_level.txt
logneuron-0.1.0.dist-info/RECORD
