Metadata-Version: 2.4
Name: logneuron
Version: 0.1.0
Summary: AI-Powered Log Analysis and Neural Network Intelligence - Coming Soon
Home-page: https://github.com/yourusername/logneuron
Author: Your Name
Author-email: email@example.com
Keywords: logging,neural networks,AI,log analysis,machine learning,monitoring
Classifier: Development Status :: 2 - Pre-Alpha
Classifier: Intended Audience :: Developers
Classifier: Intended Audience :: System Administrators
Classifier: Topic :: System :: Logging
Classifier: Topic :: Scientific/Engineering :: Artificial Intelligence
Classifier: License :: OSI Approved :: MIT License
Classifier: Programming Language :: Python :: 3
Classifier: Programming Language :: Python :: 3.7
Classifier: Programming Language :: Python :: 3.8
Classifier: Programming Language :: Python :: 3.9
Classifier: Programming Language :: Python :: 3.10
Classifier: Programming Language :: Python :: 3.11
Requires-Python: >=3.7
Requires-Dist: click>=8.0.0
Requires-Dist: colorama>=0.4.4
Dynamic: author
Dynamic: author-email
Dynamic: classifier
Dynamic: description-content-type
Dynamic: home-page
Dynamic: keywords
Dynamic: requires-dist
Dynamic: requires-python
Dynamic: summary
